Metadata-Version: 2.1
Name: deprint
Version: 0.2
Summary: Declarative Python fancy print statement
Home-page: https://github.com/rorasa/deprint
Author: Wattanit Hotrakool
Author-email: wattanit@protonmail.com
License: MIT
Download-URL: https://github.com/rorasa/deprint/archive/v_02.tar.gz
Keywords: declarative,print,fancy,color
Platform: UNKNOWN
Classifier: Development Status :: 4 - Beta
Classifier: Intended Audience :: Developers
Classifier: Topic :: Software Development
Classifier: License :: OSI Approved :: MIT License
Classifier: Programming Language :: Python :: 3
Classifier: Programming Language :: Python :: 3.4
Classifier: Programming Language :: Python :: 3.5
Classifier: Programming Language :: Python :: 3.6
Classifier: Programming Language :: Python :: 3.7
Requires-Python: >=3
